[{"project": "Smart Home IoT Platform", "title": "Device firmware updates failing", "description": "Device firmware updates failing in areas with unstable internet connection", "status": "Completed", "created_at": "2025-01-10 15:07:41.579860", "comments": []}, {"project": "Smart Home IoT Platform", "title": "High CPU usage", "description": "High CPU usage observed during real-time analytics processing", "status": "Completed", "created_at": "2025-01-10 15:08:11.935704", "comments": []}, {"project": "Mobile Banking App", "title": "Biometric authentication fails", "description": "Biometric authentication occasionally fails on specific Android devices\"", "status": "Pending", "created_at": "2025-01-10 15:09:45.870170", "comments": []}, {"project": "Mobile Banking App", "title": "transaction history loading delay", "description": "Transaction history loading time exceeds 2 seconds for accounts with 1000+ transactions", "status": "Completed", "created_at": "2025-01-10 15:10:28.379345", "comments": []}]